rainbownum/LinkedLists.py
rainbownum/RainbowCartesianSumsSim.py
rainbownum/RainbowProductsSim.py
rainbownum/RainbowSim.py
rainbownum/RainbowSumsSim.py
rainbownum/__init__.py
rainbownum-6.0.5.dist-info/LICENSE
rainbownum-6.0.5.dist-info/METADATA
rainbownum-6.0.5.dist-info/WHEEL
rainbownum-6.0.5.dist-info/top_level.txt
rainbownum-6.0.5.dist-info/RECORD
