Metadata-Version: 2.1
Name: rainbownum
Version: 6.0.5
Summary: Python package to solve anti-Schur equations
Home-page: https://github.com/pypa/sampleproject
Author: Simon Wagner
Author-email: swagner648@gmail.com
License: UNKNOWN
Platform: UNKNOWN
Requires-Dist: numpy
